fasthtml_sqlalchemy/__init__.py
fasthtml_sqlalchemy/core.py
fasthtml_sqlalchemy/models.py
fasthtml_sqlalchemy/utils.py
test/__init__.py
test/test_core.py
fasthtml_sqlalchemy-0.1.0.dist-info/LICENSE
fasthtml_sqlalchemy-0.1.0.dist-info/METADATA
fasthtml_sqlalchemy-0.1.0.dist-info/WHEEL
fasthtml_sqlalchemy-0.1.0.dist-info/top_level.txt
fasthtml_sqlalchemy-0.1.0.dist-info/RECORD
