Metadata-Version: 2.2
Name: fasthtml-sqlalchemy
Version: 0.1.0
Summary: SQLAlchemy integration for FastHTML
Home-page: https://github.com/jmsanchez-ibiza/fasthtml-sqlalchemy
Author: José María Sánchez González
Author-email: jmsanchez.ibiza@gmail.com
Classifier: Programming Language :: Python :: 3
Classifier: License :: OSI Approved :: MIT License
Classifier: Operating System :: OS Independent
Requires-Python: >=3.6
License-File: LICENSE
Requires-Dist: python-fasthtml
Requires-Dist: sqlalchemy
Dynamic: author
Dynamic: author-email
Dynamic: classifier
Dynamic: description
Dynamic: description-content-type
Dynamic: home-page
Dynamic: requires-dist
Dynamic: requires-python
Dynamic: summary
